intelinair_utils/__init__.py
intelinair_utils/__version__.py
intelinair_utils/agmri_api.py
intelinair_utils/agmri_config.py
intelinair_utils/alert_service_api.py
intelinair_utils/annotations_api.py
intelinair_utils/api.py
intelinair_utils/api_utils.py
intelinair_utils/api_wrapper.py
intelinair_utils/docker_utils.py
intelinair_utils/ec2_utils.py
intelinair_utils/efs_utils.py
intelinair_utils/elevation_metadata_service_api.py
intelinair_utils/error_logger.py
intelinair_utils/flight_service_api.py
intelinair_utils/integration_service_api.py
intelinair_utils/json_compare.py
intelinair_utils/logging_utils.py
intelinair_utils/ml_api.py
intelinair_utils/os_utils.py
intelinair_utils/pipeline_stats_api.py
intelinair_utils/planting_service_api.py
intelinair_utils/pretty_popen.py
intelinair_utils/processing_zone_service_api.py
intelinair_utils/retry_utils.py
intelinair_utils/s3_utils.py
intelinair_utils/ssm_utils.py
intelinair_utils/storage.py
intelinair_utils/storage_utils.py
intelinair_utils/token_store.py
intelinair_utils/vector_tile_service_api.py
intelinair_utils/weather_api.py
intelinair_utils-1.3.3.dist-info/METADATA
intelinair_utils-1.3.3.dist-info/WHEEL
intelinair_utils-1.3.3.dist-info/top_level.txt
intelinair_utils-1.3.3.dist-info/RECORD
