Metadata-Version: 2.4
Name: intelinair_utils
Version: 1.3.3
Requires-Dist: requests<2.32
Requires-Dist: urllib3~=1.26
Requires-Dist: boto3~=1.28
Requires-Dist: botocore~=1.31
Requires-Dist: docker==6.1.3
Requires-Dist: gitpython==3.1.31
Requires-Dist: filelock~=3.12
Requires-Dist: geojson~=3.0
Requires-Dist: deprecation~=2.1
Requires-Dist: PyYAML~=6.0
Requires-Dist: retry~=0.9
Requires-Dist: pydantic>=2.0.0
Requires-Dist: pytz~=2021.1
Requires-Dist: tenacity==8.3.0
Requires-Dist: fiona==1.9.6
Provides-Extra: shapely
Requires-Dist: shapely~=2.0; extra == "shapely"
Dynamic: description
Dynamic: description-content-type
Dynamic: provides-extra
Dynamic: requires-dist
